{
    "churches": [
        {
            "domain": "cstonemesa.org",
            "name": "Cornerstone Church, Mesa",
            "confession": "Second London Baptist Confession (1689)",
            "adopted": true,
            "source_url": "https://cstonemesa.org/what-we-believe",
            "denomination": "Reformed Baptist"
        },
        {
            "domain": "svrbc.org",
            "name": "Silicon Valley Reformed Baptist Church",
            "confession": "Second London Baptist Confession (1689)",
            "adopted": true,
            "source_url": "https://svrbc.org/beliefs/",
            "denomination": "Reformed Baptist"
        },
        {
            "domain": "morfaith.org",
            "name": "Faith Presbyterian Church",
            "confession": "Westminster Confession of Faith (1646/47)",
            "adopted": true,
            "source_url": "https://morfaith.org/helpful-links/",
            "denomination": "PCA"
        },
        {
            "domain": "sgfcjax.org",
            "name": "Sovereign Grace Family Church",
            "confession": "First London Baptist Confession (1644)",
            "adopted": true,
            "source_url": "https://sgfcjax.org/about/",
            "denomination": "Reformed Baptist"
        }
    ]
}